{
  "updated": "2026-04-24T17:30:11Z",
  "stories": [
    {
      "site": "Barna.News",
      "title": "Sant Adrià Unveils Major Industrial Estate Transformation Plan",
      "url": "https://barna.news/sant-adria-industrial-estate-transformation-plan/"
    },
    {
      "site": "Barna.News",
      "title": "Barcelona Sees 40% Rise in Repeat Offender Convictions",
      "url": "https://barna.news/barcelona-repeat-offender-convictions-rise-2025/"
    },
    {
      "site": "Catalan.News",
      "title": "Barcelona buys 14-flat building for €6.1m to expand affordable housing",
      "url": "https://catalan.news/barcelona-buys-14-flat-building-affordable-housing/"
    },
    {
      "site": "Catalan.News",
      "title": "Barcelona Metro Sets New Daily Ridership Record on Sant Jordi",
      "url": "https://catalan.news/barcelona-metro-sant-jordi-ridership-record/"
    },
    {
      "site": "RetroShell",
      "title": "Unseen Argonaut Chicken Little GBA Footage Surfaces",
      "url": "https://www.retroshell.com/unseen-argonaut-chicken-little-gba-footage-surfaces/"
    },
    {
      "site": "RetroShell",
      "title": "The Third Shift: Game Boy Horror Blends CCTV and Point-and-Click",
      "url": "https://www.retroshell.com/the-third-shift-game-boy-horror-cctv-point-and-click/"
    }
  ]
}