{
  "updated": "2026-04-29T16:27:58Z",
  "stories": [
    {
      "site": "Barna.News",
      "title": "May Day Traffic: 580,000 Vehicles Expected to Leave Barcelona",
      "url": "https://barna.news/may-day-traffic-barcelona-exodus-580000-vehicles/"
    },
    {
      "site": "Barna.News",
      "title": "Elena Martínez Leads Badalona Mossos, Prioritising Community",
      "url": "https://barna.news/elena-martinez-badalona-mossos-chief/"
    },
    {
      "site": "Catalan.News",
      "title": "Rubí tunnel reopens for freight trains after rockfall",
      "url": "https://catalan.news/rubi-tunnel-reopens-freight-trains-barcelona/"
    },
    {
      "site": "Catalan.News",
      "title": "Tortosa Music School launches Spring Concert Series",
      "url": "https://catalan.news/tortosa-music-school-spring-concerts-2026/"
    },
    {
      "site": "RetroShell",
      "title": "Magic Pockets Reflects on 25 Years of Handheld Game Development",
      "url": "https://www.retroshell.com/magic-pockets-25-years-game-boy-unity/"
    },
    {
      "site": "RetroShell",
      "title": "Ys Memoire: Revelations in Celceta Arrives on Switch",
      "url": "https://www.retroshell.com/ys-memoire-revelations-in-celceta-switch-release/"
    }
  ]
}